[
  {
    "service": "Apply for CHED Financial Assistance",
    "url": "https://ched.gov.ph/stufaps/",
    "id": "48ed16bd-dc88-4b90-a383-890caa7402b8",
    "slug": "apply-for-ched-financial-assistance",
    "published": true,
    "featured": false,
    "category": {
      "name": "Education",
      "slug": "education"
    },
    "subcategory": {
      "name": "Financial Assistance",
      "slug": "financial-assistance"
    },
    "createdAt": "2025-06-06T11:30:06.318Z",
    "updatedAt": "2025-06-06T11:30:06.318Z"
  },
  {
    "service": "Apply to the Balik Scientist Program (BSP)",
    "url": "http://bspms.dost.gov.ph/",
    "id": "9bf9ac39-0d9d-49ca-8332-b67c1838cb69",
    "slug": "apply-to-the-balik-scientist-program-bsp",
    "published": true,
    "featured": false,
    "category": {
      "name": "Education",
      "slug": "education"
    },
    "subcategory": {
      "name": "Professionals",
      "slug": "professionals"
    },
    "createdAt": "2025-06-06T11:30:06.318Z",
    "updatedAt": "2025-06-06T11:30:06.318Z"
  },
  {
    "service": "Apply for PCHRD Research Grant",
    "url": "http://www.projects.pchrd.dost.gov.ph/index.php/pms-home",
    "id": "d3f0ece7-75eb-4692-8214-ef7d0e3d6946",
    "slug": "apply-for-pchrd-research-grant",
    "published": true,
    "featured": false,
    "category": {
      "name": "Education",
      "slug": "education"
    },
    "subcategory": {
      "name": "Research and Proposal",
      "slug": "research-proposal"
    },
    "createdAt": "2025-06-06T11:30:06.318Z",
    "updatedAt": "2025-06-06T11:30:06.318Z"
  },
  {
    "service": "Apply for CHED Foreign Scholarship and Training Programs",
    "url": "https://ched.gov.ph/stufaps/",
    "id": "fbba6f06-25e8-49c9-9e83-9de02c7e31b9",
    "slug": "apply-for-ched-foreign-scholarship-and-training-programs",
    "published": true,
    "featured": false,
    "category": {
      "name": "Education",
      "slug": "education"
    },
    "subcategory": {
      "name": "Scholarships and Grants",
      "slug": "scholarships-grants"
    },
    "createdAt": "2025-06-06T11:30:06.318Z",
    "updatedAt": "2025-06-06T11:30:06.318Z"
  },
  {
    "service": "Register for a COA Training",
    "url": "https://www.coa.gov.ph/nom/",
    "id": "b917ad09-3c29-43c2-9648-da1b645d6b2d",
    "slug": "register-for-a-coa-training",
    "published": true,
    "featured": false,
    "category": {
      "name": "Education",
      "slug": "education"
    },
    "subcategory": {
      "name": "Training",
      "slug": "training"
    },
    "createdAt": "2025-06-06T11:30:06.319Z",
    "updatedAt": "2025-06-06T11:30:06.319Z"
  },
  {
    "service": "Apply for TESDA Online Program",
    "url": "https://www.e-tesda.gov.ph/login/signup.php",
    "id": "4d14d5da-ac0b-4833-a4f3-2defaa63bc2d",
    "slug": "apply-for-tesda-online-program",
    "published": true,
    "featured": false,
    "category": {
      "name": "Education",
      "slug": "education"
    },
    "subcategory": {
      "name": "Online Certificate Courses",
      "slug": "online-courses"
    },
    "createdAt": "2025-06-06T11:30:06.319Z",
    "updatedAt": "2025-06-06T11:30:06.319Z"
  },
  {
    "service": "Register Online for 2019 PSRTI Regular Training Courses",
    "url": "https://docs.google.com/forms/d/e/1FAIpQLSd8CDP2gbHIDFyD4Jxp79PL7EaTdwILuReytxiR-s7SCa1Byg/viewform",
    "id": "f127deec-ea3e-4a3a-b9bc-8c202f379bb2",
    "slug": "register-online-for-2019-psrti-regular-training-courses",
    "published": true,
    "featured": false,
    "category": {
      "name": "Education",
      "slug": "education"
    },
    "subcategory": {
      "name": "Training",
      "slug": "training"
    },
    "createdAt": "2025-06-06T11:30:06.319Z",
    "updatedAt": "2025-06-06T11:30:06.319Z"
  },
  {
    "service": "Apply for DA eLearning Certification",
    "url": "http://e-extension.gov.ph/elearning/",
    "id": "885b16fb-47f6-419b-8798-633d7808d1be",
    "slug": "apply-for-da-elearning-certification",
    "published": true,
    "featured": false,
    "category": {
      "name": "Education",
      "slug": "education"
    },
    "subcategory": {
      "name": "Online Certificate Courses",
      "slug": "online-courses"
    },
    "createdAt": "2025-06-06T11:30:06.319Z",
    "updatedAt": "2025-06-06T11:30:06.319Z"
  },
  {
    "service": "Apply for TESDA Scholarship",
    "url": "https://www.tesda.gov.ph/Barangay/",
    "id": "d0a43a7d-7d29-40f6-b5dc-633c97b9947d",
    "slug": "apply-for-tesda-scholarship",
    "published": true,
    "featured": false,
    "category": {
      "name": "Education",
      "slug": "education"
    },
    "subcategory": {
      "name": "Scholarships and Grants",
      "slug": "scholarships-grants"
    },
    "createdAt": "2025-06-06T11:30:06.319Z",
    "updatedAt": "2025-06-06T11:30:06.319Z"
  },
  {
    "service": "Apply Online for SHS Voucher Program for School Year 2019-2020",
    "url": "https://ovap.peac.org.ph/",
    "id": "ce5e2d38-33d4-419b-9f8b-c16f714332d3",
    "slug": "apply-online-for-shs-voucher-program-for-school-year-2019-2020",
    "published": true,
    "featured": false,
    "category": {
      "name": "Education",
      "slug": "education"
    },
    "subcategory": {
      "name": "Financial Assistance",
      "slug": "financial-assistance"
    },
    "createdAt": "2025-06-06T11:30:06.320Z",
    "updatedAt": "2025-06-06T11:30:06.320Z"
  }
]